verilog/memory.v
`timescale 1ns / 1ps
//states
`define START 3'b000
`define INIT 3'b001
`define WAIT_AW 3'b010
`define WAIT_W 3'b011
`define MAX_STATE 2'b011

module memory(clk,
              rst,
              aw_id,
              aw_addr,
              aw_len,
              aw_size,
              aw_burst,
              aw_cache,
              aw_prot,
              aw_qos,
              aw_region,
              //aw_user,
              aw_ready,
              aw_valid,
              w_data,
              w_strb,
              w_last,
              //w_user,
              w_ready,
              w_valid,
              b_resp,
              b_id,
              //b_user,
              b_ready,
              b_valid,
              ar_id,
              ar_addr,
              ar_len,
              ar_size,
              ar_burst,
              ar_cache,
              ar_prot,
              ar_qos,
              ar_region,
              //ar_user,
              ar_ready,
              ar_valid,
              r_id,
              r_data,
              r_resp,
              //r_user,
              r_ready,
              r_valid
              );
  parameter   DATA_WIDTH = 64;
  parameter   ADDRESS_WIDTH = 64;
  parameter   ID_WIDTH = 1;
//  parameter

//Genreal input
  input    wire                     clk;
  input    wire                     rst;
//AW
  input    wire [ID_WIDTH-1:0]      aw_id;
  input    wire [ADDRESS_WIDTH-1:0] aw_addr;
  input    wire [7:0]               aw_len;
  input    wire [2:0]               aw_size;
  input    wire [1:0]               aw_burst;
  input    wire [3:0]               aw_cache;
  input    wire [2:0]               aw_prot;
  input    wire [3:0]               aw_qos;
  input    wire [3:0]               aw_region;
  //input    wire       aw_user,
  output   wire                      aw_ready;
  input    wire                     aw_valid;
//W
  input    wire [DATA_WIDTH-1:0]    w_data;
  input    wire [7:0]               w_strb;
  input    wire                     w_last;
  //input    wire       w_user,
  output   reg                      w_ready;
  input    wire                     w_valid;
//B
  output   reg  [1:0]               b_resp;
  output   reg  [ID_WIDTH-1:0]      b_id;
  //input    wire       b_user,
  input    wire                     b_ready;
  output   reg                      b_valid;
//AR
  input    wire [ID_WIDTH-1:0]      ar_id;
  input    wire [ADDRESS_WIDTH-1:0] ar_addr;
  input    wire [7:0]               ar_len;
  input    wire [2:0]               ar_size;
  input    wire [1:0]               ar_burst;
  input    wire [3:0]               ar_cache;
  input    wire [2:0]               ar_prot;
  input    wire [3:0]               ar_qos;
  input    wire [3:0]               ar_region;
  //input    wire       ar_user,
  output   reg                      ar_ready;
  input    wire                     ar_valid;
//R
  output   reg  [ID_WIDTH:0]        r_id;
  output   reg  [DATA_WIDTH:0]      r_data;
  output   reg  [1:0]               r_resp;
  //input    wire       r_user,
  input    wire                     r_ready;
  output   reg                     r_valid;

//  enum    {START, INIT, WAIT_AW, WAIT_W}
  reg [2:0]             state, state_next;  //states
  reg                   aw_ready_next;
  reg                   w_ready_next;
  reg [1:0]             b_resp_next;
  reg [ID_WIDTH-1:0]    b_id_next;
  reg                   b_valid_next;
  reg                   ar_ready_next;
  reg [ID_WIDTH-1:0]    r_id_next;
  reg [DATA_WIDTH-1:0]  r_data_next;
  reg [1:0]             r_resp_next;
  reg                   r_valid_next;
  reg [1:0]             outstandaing_w, outstandaing_w_next;
  wire                  up_w;
  wire                  down_w;
  wire                  stall_w;



  assign stall_w = &(outstandaing_w);
  assign up_w = (aw_ready & aw_valid);
  assign down_w = (b_ready & b_valid);

  assign aw_ready = ~stall_w;
  //assign b_valid = ;

always@(posedge clk or negedge rst) begin
  if(~rst)begin
    //AW / W / R
    state     <=  `START;
//    aw_ready  <=  1'b0;
    w_ready   <=  1'b0;
    b_resp    <=  2'b00;
    b_id      <=  'b0;
    b_valid   <=  1'b0;
    ar_ready  <=  1'b0;
    r_id      <=  'b0;
    r_data    <=  'b0;
    r_resp    <=  2'b0;
    r_valid   <=  1'b0;
    //other
    outstandaing_w <= 'b0;
  end
  else begin
    state     <=  state_next;
//    aw_ready  <=  aw_ready_next;
    w_ready   <=  w_ready_next;
    b_resp    <=  b_resp_next;
    b_id      <=  b_id_next;
    b_valid   <=  b_valid_next;
    ar_ready  <=  ar_ready_next;
    r_id      <=  r_id_next;
    r_data    <=  r_data_next;
    r_resp    <=  r_resp_next;
    r_valid   <=  r_valid_next;
    //other
    outstandaing_w <= outstandaing_w_next;
  end
end
//tracking
always@(*)begin
  outstandaing_w_next = outstandaing_w;
  case({up_w,down_w})
    2'b00:begin
    //nothing happens
    end
    2'b01:begin
    //received a B resp - decrement
    outstandaing_w_next = outstandaing_w - 1;
    end
    2'b10:begin
    //recieved a AW trans - increment
    outstandaing_w_next = outstandaing_w + 1;
    end
    2'b11:begin
    //recieved B resp and AW trans
    end
  endcase
end
//main
always@(*)begin
  state_next     =    state;
//  aw_ready_next  =    ~stall_w;
  w_ready_next   =    w_ready;
  b_resp_next    =    b_resp;
  b_id_next      =    b_id;
  b_valid_next   =    b_valid;
  ar_ready_next  =    ar_ready;
  r_id_next      =    r_id;
  r_data_next    =    r_data;
  r_resp_next    =    r_resp;
  r_valid_next   =    r_valid;



  case(state)
    `START:begin
      state_next = `INIT;
    end
    `INIT:begin
      aw_ready_next = 1'b1;   //ready to recieve a write

    end
    `WAIT_AW:begin

    end
    `WAIT_W:begin
    end
    default:begin
    end
  endcase


end

endmodule

test/mem_test.sv
`include "../verilog/memory.v"
`timescale 1ns / 1ps

`define ID_WIDTH 1
`define ADDRESS_WIDTH 32
`define DATA_WIDTH 64


module mem_test;

reg random;

reg                            clk;
reg                            rst;
wire  [`ID_WIDTH-1:0]           aw_id;
wire  [`ADDRESS_WIDTH-1:0]      aw_addr;
wire  [7:0]                     aw_len;
wire  [2:0]                     aw_size;
wire  [1:0]                     aw_burst;
wire  [3:0]                     aw_cache;
wire  [2:0]                     aw_prot;
wire  [3:0]                     aw_qos;
wire  [3:0]                     aw_region;
//wire         aw_user;
wire                            aw_ready;
reg                            aw_valid;
wire  [`DATA_WIDTH-1:0]         w_data;
wire  [7:0]                     w_strb;
wire                            w_last;
//wire         w_user;
wire                            w_ready;
wire                            w_valid;
wire  [1:0]                     b_resp;
wire  [`ID_WIDTH-1:0]           b_id;
//wire         b_user;
wire                            b_ready;
wire                            b_valid;
wire  [`ID_WIDTH-1:0]           ar_id;
wire  [`ADDRESS_WIDTH-1:0]      ar_addr;
wire  [7:0]                     ar_len;
wire  [2:0]                     ar_size;
wire  [1:0]                     ar_burst;
wire  [3:0]                     ar_cache;
wire  [2:0]                     ar_prot;
wire  [3:0]                     ar_qos;
wire  [3:0]                     ar_region;
//wire                            ar_user;
wire                            ar_ready;
wire                            ar_valid;
wire  [`ID_WIDTH:0]             r_id;
wire  [`DATA_WIDTH:0]           r_data;
wire  [1:0]                     r_resp;
wire                            r_ready;
wire                            r_valid;

//main
initial begin
  rst = 1;
  clk = 0;
  #10;
  rst = 0;
  #10;
  rst = 1;
  #10;
  aw_valid =1;
  #10;
  aw_valid =0;
  #10;
  aw_valid =1;
  #10;
  aw_valid =0;
  #10;
  aw_valid =1;
  #10;
  aw_valid =0;
  #10;
  aw_valid =1;
  #10;
  aw_valid =0;
  #10;
  m1.outstandaing_w = m1.outstandaing_w + 1;
  #1000;
  random = 0;
  #10 random =1;
  #10 $finish;
end

//clock

always #5 clk = !clk;

//report
initial begin
    $dumpfile("sim.vcd");
    $dumpvars(0,mem_test);
    $monitor("%t\tState: %0d",$time, m1.state);
    $monitor("At time %t, rst = %h (%0d)",$time, rst, rst);
end
 memory #(
   .DATA_WIDTH(`DATA_WIDTH),
   .ADDRESS_WIDTH(`ADDRESS_WIDTH),
   .ID_WIDTH(`ID_WIDTH))
        m1 (  .clk(clk),
              .rst(rst),
              .aw_id(aw_id),
              .aw_addr(aw_addr),
              .aw_len(aw_len),
              .aw_size(aw_size),
              .aw_burst(aw_burst),
              .aw_cache(aw_cache),
              .aw_prot(aw_prot),
              .aw_qos(aw_qos),
              .aw_region(aw_region),
            //.aw_user,
              .aw_ready(aw_ready),
              .aw_valid(aw_valid),
              .w_data(w_data),
              .w_strb(w_strb),
              .w_last(w_last),
            //.w_user,
              .w_ready(w_ready),
              .w_valid(w_valid),
              .b_resp(b_resp),
              .b_id(b_id),
            //.b_user,
              .b_ready(b_ready),
              .b_valid(b_valid),
              .ar_id(ar_id),
              .ar_addr(ar_addr),
              .ar_len(ar_len),
              .ar_size(ar_size),
              .ar_burst(ar_burst),
              .ar_cache(ar_cache),
              .ar_prot(ar_prot),
              .ar_qos(ar_qos),
              .ar_region(ar_region),
            //.ar_user,
              .ar_ready(ar_ready),
              .ar_valid(ar_valid),
              .r_id(r_id),
              .r_data(r_data),
              .r_resp(r_resp),
            //.r_user,
              .r_ready(r_ready),
              .r_valid(r_valid)
              );
endmodule //mem_test

test/sim.vcd
$date
	Wed Feb 28 00:14:25 2018
$end
$version
	Icarus Verilog
$end
$timescale
	1ps
$end
$scope module mem_test $end
$var wire 32 ! ar_addr [31:0] $end
$var wire 2 " ar_burst [1:0] $end
$var wire 4 # ar_cache [3:0] $end
$var wire 1 $ ar_id $end
$var wire 8 % ar_len [7:0] $end
$var wire 3 & ar_prot [2:0] $end
$var wire 4 ' ar_qos [3:0] $end
$var wire 1 ( ar_ready $end
$var wire 4 ) ar_region [3:0] $end
$var wire 3 * ar_size [2:0] $end
$var wire 1 + ar_valid $end
$var wire 32 , aw_addr [31:0] $end
$var wire 2 - aw_burst [1:0] $end
$var wire 4 . aw_cache [3:0] $end
$var wire 1 / aw_id $end
$var wire 8 0 aw_len [7:0] $end
$var wire 3 1 aw_prot [2:0] $end
$var wire 4 2 aw_qos [3:0] $end
$var wire 1 3 aw_ready $end
$var wire 4 4 aw_region [3:0] $end
$var wire 3 5 aw_size [2:0] $end
$var wire 1 6 b_id $end
$var wire 1 7 b_ready $end
$var wire 2 8 b_resp [1:0] $end
$var wire 1 9 b_valid $end
$var wire 65 : r_data [64:0] $end
$var wire 2 ; r_id [1:0] $end
$var wire 1 < r_ready $end
$var wire 2 = r_resp [1:0] $end
$var wire 1 > r_valid $end
$var wire 64 ? w_data [63:0] $end
$var wire 1 @ w_last $end
$var wire 1 A w_ready $end
$var wire 8 B w_strb [7:0] $end
$var wire 1 C w_valid $end
$var reg 1 D aw_valid $end
$var reg 1 E clk $end
$var reg 1 F random $end
$var reg 1 G rst $end
$scope module m1 $end
$var wire 32 H ar_addr [31:0] $end
$var wire 2 I ar_burst [1:0] $end
$var wire 4 J ar_cache [3:0] $end
$var wire 1 $ ar_id $end
$var wire 8 K ar_len [7:0] $end
$var wire 3 L ar_prot [2:0] $end
$var wire 4 M ar_qos [3:0] $end
$var wire 4 N ar_region [3:0] $end
$var wire 3 O ar_size [2:0] $end
$var wire 1 + ar_valid $end
$var wire 32 P aw_addr [31:0] $end
$var wire 2 Q aw_burst [1:0] $end
$var wire 4 R aw_cache [3:0] $end
$var wire 1 / aw_id $end
$var wire 8 S aw_len [7:0] $end
$var wire 3 T aw_prot [2:0] $end
$var wire 4 U aw_qos [3:0] $end
$var wire 1 3 aw_ready $end
$var wire 4 V aw_region [3:0] $end
$var wire 3 W aw_size [2:0] $end
$var wire 1 X aw_valid $end
$var wire 1 7 b_ready $end
$var wire 1 Y clk $end
$var wire 1 Z down_w $end
$var wire 1 < r_ready $end
$var wire 1 [ rst $end
$var wire 1 \ stall_w $end
$var wire 1 ] up_w $end
$var wire 64 ^ w_data [63:0] $end
$var wire 1 @ w_last $end
$var wire 8 _ w_strb [7:0] $end
$var wire 1 C w_valid $end
$var reg 1 ` ar_ready $end
$var reg 1 a ar_ready_next $end
$var reg 1 b aw_ready_next $end
$var reg 1 c b_id $end
$var reg 1 d b_id_next $end
$var reg 2 e b_resp [1:0] $end
$var reg 2 f b_resp_next [1:0] $end
$var reg 1 g b_valid $end
$var reg 1 h b_valid_next $end
$var reg 2 i outstandaing_w [1:0] $end
$var reg 2 j outstandaing_w_next [1:0] $end
$var reg 65 k r_data [64:0] $end
$var reg 64 l r_data_next [63:0] $end
$var reg 2 m r_id [1:0] $end
$var reg 1 n r_id_next $end
$var reg 2 o r_resp [1:0] $end
$var reg 2 p r_resp_next [1:0] $end
$var reg 1 q r_valid $end
$var reg 1 r r_valid_next $end
$var reg 3 s state [2:0] $end
$var reg 3 t state_next [2:0] $end
$var reg 1 u w_ready $end
$var reg 1 v w_ready_next $end
$upscope $end
$upscope $end
$enddefinitions $end
#0
$dumpvars
xv
xu
bx t
bx s
xr
xq
bx p
bx o
xn
bx m
bx l
bx k
bx j
bx i
xh
xg
bx f
bx e
xd
xc
xb
xa
x`
bz _
bz ^
x]
x\
1[
xZ
0Y
xX
bz W
bz V
bz U
bz T
bz S
bz R
bz Q
bz P
bz O
bz N
bz M
bz L
bz K
bz J
bz I
bz H
1G
xF
0E
xD
zC
bz B
xA
z@
bz ?
x>
bx =
z<
bx ;
bx :
x9
bx 8
z7
x6
bz 5
bz 4
x3
bz 2
bz 1
bz 0
z/
bz .
bz -
bz ,
z+
bz *
bz )
x(
bz '
bz &
bz %
z$
bz #
bz "
bz !
$end
#5000
b0xxxxxxxxxxxxxxxxxxxxxxxxxxxxxxxxxxxxxxxxxxxxxxxxxxxxxxxxxxxxxxxx k
b0xxxxxxxxxxxxxxxxxxxxxxxxxxxxxxxxxxxxxxxxxxxxxxxxxxxxxxxxxxxxxxxx :
b0x m
b0x ;
1E
1Y
#10000
b0 j
13
0Z
0r
b0 p
b0 l
0n
0a
0h
0d
b0 f
0v
b1 t
b0 i
0\
0q
0>
b0 o
b0 =
b0 k
b0 :
b0 m
b0 ;
0`
0(
0g
09
0c
06
b0 e
b0 8
0u
0A
b0 s
0E
0Y
0G
0[
#15000
1E
1Y
#20000
0E
0Y
1G
1[
#25000
1b
b1 s
1E
1Y
#30000
b1 j
1]
0E
0Y
1D
1X
#35000
b10 j
b1 i
1E
1Y
#40000
b1 j
0]
0E
0Y
0D
0X
#45000
1E
1Y
#50000
b10 j
1]
0E
0Y
1D
1X
#55000
b11 j
b10 i
1E
1Y
#60000
b10 j
0]
0E
0Y
0D
0X
#65000
1E
1Y
#70000
b11 j
1]
0E
0Y
1D
1X
#75000
0]
b11 j
03
b11 i
1\
1E
1Y
#80000
0E
0Y
0D
0X
#85000
1E
1Y
#90000
0E
0Y
1D
1X
#95000
1E
1Y
#100000
0E
0Y
0D
0X
#105000
1E
1Y
#110000
b0 j
13
0E
0Y
b0 i
0\
